{
  "id": "andrei-gromyko",
  "type": "person",
  "name": {
    "he": "אנדריי גרומיקו"
  },
  "bio": {
    "he": "מדינאי ודיפלומט סובייטי, שכיהן כשגריר ברית המועצות באו״ם, שר החוץ הסובייטי ולימים יו״ר הסובייט העליון. ב-29 בנובמבר 1947, כנציג ברית המועצות באו״ם, נמנה עם התומכים באישור תוכנית החלוקה של ארץ ישראל ונשא נאום שתמך בזכות העם היהודי למדינה משלו — עמדה שסללה את הדרך להכרת ברית המועצות בישראל ב-1948."
  },
  "lifespan": {
    "start": "1909-07-18",
    "end": "1989-07-02"
  },
  "categoryIds": [
    "leaders"
  ],
  "importance": 42,
  "sources": [
    {
      "title": {
        "he": "אנדריי גרומיקו — ויקיפדיה"
      },
      "url": "https://he.wikipedia.org/wiki/%D7%90%D7%A0%D7%93%D7%A8%D7%99%D7%99_%D7%92%D7%A8%D7%95%D7%9E%D7%99%D7%A7%D7%95",
      "kind": "encyclopedia"
    }
  ]
}
