{
  "id": "yaakov-heruti",
  "type": "person",
  "name": {
    "he": "יעקב חרותי"
  },
  "bio": {
    "he": "עורך דין ולוחם לח\"י, ממייסדי ומפקדי \"מחתרת צריפין\" (מלכות ישראל) שפעלה ב-1952–1953 ותכננה פיגועים נגד נציגויות ברית המועצות וצ'כוסלובקיה; נידון ל-10 שנות מאסר וזכה לחנינה מדוד בן-גוריון ב-1955. לאחר רצח ישראל קסטנר ב-1957 נעצר בחשד למעורבות בארגון טרור אך זוכה מהאישום, והורשע רק בעבירה קלה של הפצת כרוזים. בהמשך חייו התמחה בדיני מקרקעין וייעץ למִנהל האזרחי בנושאי אדמות בשטחים."
  },
  "lifespan": {
    "start": "1927-01-15",
    "end": "2022-07-28"
  },
  "categoryIds": [
    "military"
  ],
  "importance": 16,
  "sources": [
    {
      "title": {
        "he": "יעקב חרותי – ויקיפדיה"
      },
      "url": "https://he.wikipedia.org/wiki/%D7%99%D7%A2%D7%A7%D7%91_%D7%97%D7%A8%D7%95%D7%AA%D7%99",
      "kind": "encyclopedia"
    }
  ]
}
