{
  "id": "madrid-conference",
  "type": "event",
  "title": {
    "he": "ועידת מדריד"
  },
  "description": {
    "he": "ועידת שלום בינלאומית באוקטובר 1991 שכינסה לראשונה את ישראל ומדינות ערב והפלסטינים לשיחות ישירות; פתחה עידן של תהליכים מדיניים בשנות התשעים."
  },
  "dates": {
    "start": "1991-10-30"
  },
  "importance": 40,
  "categoryIds": [
    "state-politics"
  ],
  "regionIds": [
    "israel"
  ],
  "sources": [
    {
      "title": {
        "he": "ויקיפדיה העברית"
      },
      "url": "https://he.wikipedia.org/wiki/ועידת_מדריד_(1991)",
      "kind": "encyclopedia"
    }
  ]
}
